scaching/__init__.py
scaching/main.py
scaching/semantic_caching.py
scaching/test_semantic_caching.py
scaching-0.0.1.dist-info/METADATA
scaching-0.0.1.dist-info/WHEEL
scaching-0.0.1.dist-info/top_level.txt
scaching-0.0.1.dist-info/RECORD
