Metadata-Version: 2.1
Name: scaching
Version: 0.0.1
Summary: Semantic Caching with Python
Author: Eray Eroğlu
Author-email: erayeroglu07@email.com
Keywords: python,first package
Classifier: Development Status :: 5 - Production/Stable
Classifier: Intended Audience :: Developers
Classifier: Programming Language :: Python :: 3
Classifier: Operating System :: MacOS :: MacOS X
Classifier: Operating System :: Microsoft :: Windows
Classifier: Operating System :: POSIX :: Linux
